V_page_extract/__init__.py
V_page_extract/main.py
V_page_extract/tesr/__init__.py
V_page_extract/tesr/tes.py
V_page_extract-0.1.4.dist-info/METADATA
V_page_extract-0.1.4.dist-info/WHEEL
V_page_extract-0.1.4.dist-info/entry_points.txt
V_page_extract-0.1.4.dist-info/top_level.txt
V_page_extract-0.1.4.dist-info/RECORD
