Metadata-Version: 2.1
Name: V_page_extract
Version: 0.1.4
Summary: page extractor
Author: Vadym S
Author-email: olko.soroka3@gmail.com
Requires-Dist: PyPDF2>=1.26.0
Requires-Dist: matplotlib>=3.0.0
Requires-Dist: numpy>=1.18.0
Requires-Dist: os
